SecretsProvider/__init__.py
SecretsProvider/main.py
secretsprovider-2.0.3.dist-info/METADATA
secretsprovider-2.0.3.dist-info/WHEEL
secretsprovider-2.0.3.dist-info/RECORD
