Metadata-Version: 2.4
Name: SecretsProvider
Version: 2.0.3
Summary: A package to handle secrets in Python
Project-URL: Homepage, https://github.com/NaaVRE/SecretsProvider.git
Author-email: Koen Greuell <koen.greuell@lifewatch.eu>
License-Expression: Apache-2.0
Classifier: Operating System :: OS Independent
Classifier: Programming Language :: Python :: 3
Requires-Python: >=3.8
Requires-Dist: python-dotenv>=1.0.1
